molgenis_emx2_staging_migrator/__init__.py
molgenis_emx2_staging_migrator/constants.py
molgenis_emx2_staging_migrator/migrator.py
molgenis_emx2_staging_migrator/utils.py
molgenis_emx2_staging_migrator-13.19.0.dist-info/METADATA
molgenis_emx2_staging_migrator-13.19.0.dist-info/WHEEL
molgenis_emx2_staging_migrator-13.19.0.dist-info/top_level.txt
molgenis_emx2_staging_migrator-13.19.0.dist-info/RECORD
