Metadata-Version: 2.4
Name: molgenis-emx2-staging-migrator
Version: 13.19.0
Summary: Python package for migrating Molgenis EMX2 staging areas to a catalogue.
Classifier: Programming Language :: Python :: 3
Classifier: License :: OSI Approved :: GNU Lesser General Public License v3 (LGPLv3)
Classifier: Operating System :: OS Independent
Requires-Python: >=3.10
Requires-Dist: molgenis-emx2-pyclient>=11.61.2
Requires-Dist: requests>=2.32.3
Requires-Dist: pandas>=2.2.2
